README.md
setup.cfg
setup.py
wrecon/__init__.py
wrecon/wrecon.py
wrecon.egg-info/PKG-INFO
wrecon.egg-info/SOURCES.txt
wrecon.egg-info/dependency_links.txt
wrecon.egg-info/entry_points.txt
wrecon.egg-info/not-zip-safe
wrecon.egg-info/requires.txt
wrecon.egg-info/top_level.txt