Metadata-Version: 2.1
Name: wrecon
Version: 0.5
Summary: WRecon is an open source no intussive web scanner. It is designed to discover all URL in a website recursively, without using bruteforce or unauthorized access. It comes with a camouflage engine and nice features for pentesting.
Home-page: https://github.com/fabiodelgadopereira/wrecon
Author: Fabio Delgado
Author-email: fabio_delgado2@hotmail.com
License: MIT
Platform: UNKNOWN
Requires-Python: >=3.7
